Metadata-Version: 2.1
Name: metrics-computation
Version: 0.0.2
Summary: Given a True beta vector and a predicted beta vector, computes a set of metrics such as true positive rate, recall, etc
Home-page: https://github.com/alvaromc317/metrics_computation
Author: Alvaro Mendez Civieta
Author-email: almendez@est-econ.uc3m.es
License: GNU General Public License
Keywords: High dimensional regression,metrics,true positive rate,true negative rate,precision,recall,f-score
Platform: UNKNOWN
Requires-Python: >=3.5
